Metadata-Version: 2.1
Name: PyDictAPI
Version: 1.6.0
Summary: An advanced Dictionary and Translator Module for Python
Home-page: https://github.com/imshawan/PyDictAPI
Author: Shawan Mandal
Author-email: imshawan.dev049@gmail.com
License: UNKNOWN
Platform: UNKNOWN
Classifier: Intended Audience :: Education
Classifier: License :: OSI Approved :: MIT License
Classifier: Operating System :: OS Independent
Classifier: Programming Language :: Python :: 3
